[
  {
    "component": "Button",
    "sessionId": "sessions/610241997296214823",
    "title": "Refactor: Button",
    "startTime": "2025-12-10T13:50:00",
    "status": "created"
  },
  {
    "component": "Alert",
    "sessionId": "sessions/2136897921091547824",
    "title": "Refactor: Alert",
    "startTime": "2025-12-10T14:10:00",
    "status": "created"
  },
  {
    "component": "AspectRatio",
    "sessionId": "sessions/2338180863383334968",
    "title": "Refactor: AspectRatio",
    "startTime": "2025-12-10T14:10:00",
    "status": "created"
  },
  {
    "component": "Avatar",
    "sessionId": "sessions/1148533280855249655",
    "title": "Refactor: Avatar",
    "startTime": "2025-12-10T14:10:00",
    "status": "created"
  },
  {
    "component": "Badge",
    "sessionId": "sessions/12109643611567383686",
    "title": "Refactor: Badge",
    "startTime": "2025-12-10T14:10:00",
    "status": "created"
  },
  {
    "component": "Checkbox",
    "sessionId": "sessions/16381553164015630085",
    "title": "Refactor: Checkbox",
    "startTime": "2025-12-10T14:10:00",
    "status": "created"
  },
  {
    "component": "Input",
    "sessionId": "sessions/8542818502101652215",
    "title": "Refactor: Input",
    "startTime": "2025-12-10T14:10:00",
    "status": "created"
  },
  {
    "component": "Kbd",
    "sessionId": "sessions/14867311965304767966",
    "title": "Refactor: Kbd",
    "startTime": "2025-12-10T14:10:00",
    "status": "created"
  },
  {
    "component": "Label",
    "sessionId": "sessions/11687168199851868491",
    "title": "Refactor: Label",
    "startTime": "2025-12-10T14:10:00",
    "status": "created"
  },
  {
    "component": "Progress",
    "sessionId": "sessions/3108745722377050731",
    "title": "Refactor: Progress",
    "startTime": "2025-12-10T14:10:00",
    "status": "created"
  },
  {
    "component": "ScrollArea",
    "sessionId": "sessions/15656747583367078005",
    "title": "Refactor: ScrollArea",
    "startTime": "2025-12-10T14:10:00",
    "status": "created"
  },
  {
    "component": "Separator",
    "sessionId": "sessions/4936617615332842869",
    "title": "Refactor: Separator",
    "startTime": "2025-12-10T16:30:06.967533",
    "status": "created"
  },
  {
    "component": "Skeleton",
    "sessionId": "sessions/10260442856057085890",
    "title": "Refactor: Skeleton",
    "startTime": "2025-12-10T16:30:10.332697",
    "status": "created"
  },
  {
    "component": "Slider",
    "sessionId": "sessions/778227454201825430",
    "title": "Refactor: Slider",
    "startTime": "2025-12-10T16:30:13.743864",
    "status": "created"
  },
  {
    "component": "Spinner",
    "sessionId": "sessions/7310869521230919839",
    "title": "Refactor: Spinner",
    "startTime": "2025-12-10T16:30:16.702825",
    "status": "created"
  },
  {
    "component": "Stack",
    "sessionId": "sessions/10634616901043083404",
    "title": "Refactor: Stack",
    "startTime": "2025-12-10T16:30:19.551206",
    "status": "created"
  },
  {
    "component": "Switch",
    "sessionId": "sessions/11155016287718424448",
    "title": "Refactor: Switch",
    "startTime": "2025-12-10T16:30:22.792824",
    "status": "created"
  },
  {
    "component": "Textarea",
    "sessionId": "sessions/11512241054233672717",
    "title": "Refactor: Textarea",
    "startTime": "2025-12-10T16:30:25.778241",
    "status": "created"
  },
  {
    "component": "Toggle",
    "sessionId": "sessions/18249884321034393256",
    "title": "Refactor: Toggle",
    "startTime": "2025-12-10T16:30:28.789438",
    "status": "created"
  },
  {
    "component": "Typography",
    "sessionId": "sessions/18114802174976461377",
    "title": "Refactor: Typography",
    "startTime": "2025-12-10T16:30:32.136739",
    "status": "created"
  },
  {
    "component": "NavLink",
    "sessionId": "sessions/10346208566698505321",
    "title": "Refactor: NavLink",
    "startTime": "2025-12-10T16:30:35.075555",
    "status": "created"
  },
  {
    "component": "Logo",
    "sessionId": "sessions/1597636896550233068",
    "title": "Refactor: Logo",
    "startTime": "2025-12-10T16:30:38.243561",
    "status": "created"
  },
  {
    "component": "Dot",
    "sessionId": "sessions/1776409349368513443",
    "title": "Refactor: Dot",
    "startTime": "2025-12-10T16:30:41.479401",
    "status": "created"
  },
  {
    "component": "Accordion",
    "sessionId": "sessions/13234786001609420213",
    "title": "Refactor: Accordion",
    "startTime": "2025-12-10T20:12:05.281004",
    "status": "created"
  },
  {
    "component": "AlertDialog",
    "sessionId": "sessions/5195840750227181812",
    "title": "Refactor: AlertDialog",
    "startTime": "2025-12-10T20:12:08.103828",
    "status": "created"
  },
  {
    "component": "AvatarGroup",
    "sessionId": "sessions/7039064243706002828",
    "title": "Refactor: AvatarGroup",
    "startTime": "2025-12-10T20:12:11.225695",
    "status": "created"
  },
  {
    "component": "BadgeCounter",
    "sessionId": "sessions/8539695813391814611",
    "title": "Refactor: BadgeCounter",
    "startTime": "2025-12-10T20:12:14.262340",
    "status": "created"
  },
  {
    "component": "Breadcrumb",
    "sessionId": "sessions/4316336560679448423",
    "title": "Refactor: Breadcrumb",
    "startTime": "2025-12-10T20:12:17.608904",
    "status": "created"
  },
  {
    "component": "ButtonGroup",
    "sessionId": "sessions/4709596245149598815",
    "title": "Refactor: ButtonGroup",
    "startTime": "2025-12-10T20:12:20.565700",
    "status": "created"
  },
  {
    "component": "Calendar",
    "sessionId": "sessions/14540676105822444238",
    "title": "Refactor: Calendar",
    "startTime": "2025-12-10T20:12:23.412081",
    "status": "created"
  },
  {
    "component": "Card",
    "sessionId": "sessions/320302576934023926",
    "title": "Refactor: Card",
    "startTime": "2025-12-10T20:12:26.343470",
    "status": "created"
  },
  {
    "component": "Collapsible",
    "sessionId": "sessions/6310328591986706203",
    "title": "Refactor: Collapsible",
    "startTime": "2025-12-10T20:12:29.652115",
    "status": "created"
  },
  {
    "component": "ComponentErrorBoundary",
    "sessionId": "sessions/8892522776144247961",
    "title": "Refactor: ComponentErrorBoundary",
    "startTime": "2025-12-10T20:12:32.401991",
    "status": "created"
  },
  {
    "component": "ContextMenu",
    "sessionId": "sessions/1978306470874344731",
    "title": "Refactor: ContextMenu",
    "startTime": "2025-12-10T20:12:35.430202",
    "status": "created"
  },
  {
    "component": "DatePicker",
    "sessionId": "sessions/14883937903997332791",
    "title": "Refactor: DatePicker",
    "startTime": "2025-12-10T20:12:38.207982",
    "status": "created"
  },
  {
    "component": "Dialog",
    "sessionId": "sessions/17340227528443321775",
    "title": "Refactor: Dialog",
    "startTime": "2025-12-10T20:12:41.428478",
    "status": "created"
  },
  {
    "component": "Drawer",
    "sessionId": "sessions/10048527228131549591",
    "title": "Refactor: Drawer",
    "startTime": "2025-12-10T20:12:44.152375",
    "status": "created"
  },
  {
    "component": "Empty",
    "sessionId": "sessions/7290256657560021614",
    "title": "Refactor: Empty",
    "startTime": "2025-12-10T20:12:47.002072",
    "status": "created"
  },
  {
    "component": "Field",
    "sessionId": "sessions/3292206753898807227",
    "title": "Refactor: Field",
    "startTime": "2025-12-10T20:12:49.758559",
    "status": "created"
  },
  {
    "component": "HoverCard",
    "sessionId": "sessions/15243738505111002308",
    "title": "Refactor: HoverCard",
    "startTime": "2025-12-10T20:12:52.877928",
    "status": "created"
  },
  {
    "component": "InputGroup",
    "sessionId": "sessions/4270437734858115015",
    "title": "Refactor: InputGroup",
    "startTime": "2025-12-10T20:12:55.977315",
    "status": "created"
  },
  {
    "component": "Item",
    "sessionId": "sessions/2789341558441904475",
    "title": "Refactor: Item",
    "startTime": "2025-12-10T20:12:58.620888",
    "status": "created"
  },
  {
    "component": "Menubar",
    "sessionId": "sessions/5088267931091244066",
    "title": "Refactor: Menubar",
    "startTime": "2025-12-10T20:13:01.623792",
    "status": "created"
  },
  {
    "component": "MonthsPicker",
    "sessionId": "sessions/12397012482561653107",
    "title": "Refactor: MonthsPicker",
    "startTime": "2025-12-10T20:13:05.218062",
    "status": "created"
  },
  {
    "component": "NativeSelect",
    "sessionId": "sessions/10394312203446883790",
    "title": "Refactor: NativeSelect",
    "startTime": "2025-12-10T20:13:08.181260",
    "status": "created"
  },
  {
    "component": "NavigationMenu",
    "sessionId": "sessions/11166194293803602168",
    "title": "Refactor: NavigationMenu",
    "startTime": "2025-12-10T20:13:11.086793",
    "status": "created"
  },
  {
    "component": "OTPInput",
    "sessionId": "sessions/11122409379249019210",
    "title": "Refactor: OTPInput",
    "startTime": "2025-12-10T20:13:13.760487",
    "status": "created"
  },
  {
    "component": "Pagination",
    "sessionId": "sessions/6559553365986822872",
    "title": "Refactor: Pagination",
    "startTime": "2025-12-10T20:13:17.182332",
    "status": "created"
  },
  {
    "component": "Popover",
    "sessionId": "sessions/17003105335214172241",
    "title": "Refactor: Popover",
    "startTime": "2025-12-10T20:13:20.013779",
    "status": "created"
  },
  {
    "component": "RadioGroup",
    "sessionId": "sessions/18192417753922812080",
    "title": "Refactor: RadioGroup",
    "startTime": "2025-12-10T20:13:22.951838",
    "status": "created"
  },
  {
    "component": "Resizable",
    "sessionId": "sessions/16652700841167769193",
    "title": "Refactor: Resizable",
    "startTime": "2025-12-10T20:13:25.923537",
    "status": "created"
  },
  {
    "component": "Select",
    "sessionId": "sessions/16275853611313902001",
    "title": "Refactor: Select",
    "startTime": "2025-12-10T20:13:29.026008",
    "status": "created"
  },
  {
    "component": "Sheet",
    "sessionId": "sessions/16174188485070666716",
    "title": "Refactor: Sheet",
    "startTime": "2025-12-10T20:13:32.027910",
    "status": "created"
  },
  {
    "component": "Sonner",
    "sessionId": "sessions/13935720257890393344",
    "title": "Refactor: Sonner",
    "startTime": "2025-12-10T20:13:34.845473",
    "status": "created"
  },
  {
    "component": "StarRating",
    "sessionId": "sessions/4187206820159755427",
    "title": "Refactor: StarRating",
    "startTime": "2025-12-10T20:13:37.788996",
    "status": "created"
  },
  {
    "component": "Stepper",
    "sessionId": "sessions/5624900774852206456",
    "title": "Refactor: Stepper",
    "startTime": "2025-12-10T20:13:40.856061",
    "status": "created"
  },
  {
    "component": "Table",
    "sessionId": "sessions/12465433611061990311",
    "title": "Refactor: Table",
    "startTime": "2025-12-10T20:13:44.069871",
    "status": "created"
  },
  {
    "component": "Tabs",
    "sessionId": "sessions/1819439988750732430",
    "title": "Refactor: Tabs",
    "startTime": "2025-12-10T20:13:46.844631",
    "status": "created"
  },
  {
    "component": "Toast",
    "sessionId": "sessions/3603143551838217776",
    "title": "Refactor: Toast",
    "startTime": "2025-12-10T20:13:49.748968",
    "status": "created"
  },
  {
    "component": "ToggleGroup",
    "sessionId": "sessions/8470821535678544455",
    "title": "Refactor: ToggleGroup",
    "startTime": "2025-12-10T20:13:53.301585",
    "status": "created"
  },
  {
    "component": "Tooltip",
    "sessionId": "sessions/12776585266854353059",
    "title": "Refactor: Tooltip",
    "startTime": "2025-12-10T20:13:56.285370",
    "status": "created"
  },
  {
    "component": "MetricCard",
    "sessionId": "sessions/10898956778686554297",
    "title": "Refactor: MetricCard",
    "startTime": "2025-12-10T20:13:59.410328",
    "status": "created"
  },
  {
    "component": "NavGroup",
    "sessionId": "sessions/9126108579410547741",
    "title": "Refactor: NavGroup",
    "startTime": "2025-12-10T20:14:02.266985",
    "status": "created"
  },
  {
    "component": "ChartContainer",
    "sessionId": "sessions/502331359689095340",
    "title": "Refactor: ChartContainer",
    "startTime": "2025-12-10T20:14:05.847178",
    "status": "created"
  },
  {
    "component": "RadialChartContent",
    "sessionId": "sessions/14369341608115368303",
    "title": "Refactor: RadialChartContent",
    "startTime": "2025-12-10T20:14:08.711417",
    "status": "created"
  },
  {
    "component": "HorizontalBarGroup",
    "sessionId": "sessions/11932240997742443029",
    "title": "Refactor: HorizontalBarGroup",
    "startTime": "2025-12-10T20:14:11.816125",
    "status": "created"
  },
  {
    "component": "Collapsible",
    "sessionId": "sessions/7658640210671527458",
    "title": "Refactor: Collapsible",
    "startTime": "2025-12-11T13:55:30.098672",
    "status": "created"
  },
  {
    "component": "Empty",
    "sessionId": "sessions/4631933430795898581",
    "title": "Refactor: Empty",
    "startTime": "2025-12-11T13:55:33.201431",
    "status": "created"
  },
  {
    "component": "Sonner",
    "sessionId": "sessions/14881574663270584859",
    "title": "Refactor: Sonner",
    "startTime": "2025-12-11T13:55:36.929183",
    "status": "created"
  },
  {
    "component": "MetricCard",
    "sessionId": "sessions/5069382544934931143",
    "title": "Refactor: MetricCard",
    "startTime": "2025-12-11T13:55:39.970529",
    "status": "created"
  },
  {
    "component": "Autocomplete",
    "sessionId": "sessions/12141032162089402903",
    "title": "Refactor: Autocomplete",
    "startTime": "2025-12-11T14:00:29.017753",
    "status": "created"
  },
  {
    "component": "Carousel",
    "sessionId": "sessions/16655945337089654225",
    "title": "Refactor: Carousel",
    "startTime": "2025-12-11T14:00:32.155023",
    "status": "created"
  },
  {
    "component": "Charts",
    "sessionId": "sessions/6953055481132063120",
    "title": "Refactor: Charts",
    "startTime": "2025-12-11T14:00:35.544424",
    "status": "created"
  },
  {
    "component": "Command",
    "sessionId": "sessions/15065560455683038732",
    "title": "Refactor: Command",
    "startTime": "2025-12-11T14:00:38.400671",
    "status": "created"
  },
  {
    "component": "DashboardShell",
    "sessionId": "sessions/779009443528531382",
    "title": "Refactor: DashboardShell",
    "startTime": "2025-12-11T14:00:43.206324",
    "status": "created"
  },
  {
    "component": "DataTable",
    "sessionId": "sessions/13767077277124387128",
    "title": "Refactor: DataTable",
    "startTime": "2025-12-11T14:00:49.999530",
    "status": "created"
  },
  {
    "component": "FileUpload",
    "sessionId": "sessions/3481820733678820910",
    "title": "Refactor: FileUpload",
    "startTime": "2025-12-11T14:00:53.041989",
    "status": "created"
  },
  {
    "component": "Form",
    "sessionId": "sessions/17340492855929332889",
    "title": "Refactor: Form",
    "startTime": "2025-12-11T14:00:55.817999",
    "status": "created"
  },
  {
    "component": "RichText",
    "sessionId": "sessions/7538230852032593207",
    "title": "Refactor: RichText",
    "startTime": "2025-12-11T14:00:58.776384",
    "status": "created"
  },
  {
    "component": "Sidebar",
    "sessionId": "sessions/9686361760491690799",
    "title": "Refactor: Sidebar",
    "startTime": "2025-12-11T14:01:01.597514",
    "status": "created"
  },
  {
    "component": "Timeline",
    "sessionId": "sessions/16855601768955863358",
    "title": "Refactor: Timeline",
    "startTime": "2025-12-11T14:01:08.600228",
    "status": "created"
  },
  {
    "component": "KPIGrid",
    "sessionId": "sessions/1086488643477629696",
    "title": "Refactor: KPIGrid",
    "startTime": "2025-12-11T14:01:11.660847",
    "status": "created"
  },
  {
    "component": "TimeSeriesChart",
    "sessionId": "sessions/6114053986383402782",
    "title": "Refactor: TimeSeriesChart",
    "startTime": "2025-12-11T14:01:16.401945",
    "status": "created"
  },
  {
    "component": "GaugeChart",
    "sessionId": "sessions/10555113743901936004",
    "title": "Refactor: GaugeChart",
    "startTime": "2025-12-11T14:01:19.249869",
    "status": "created"
  },
  {
    "component": "RankingChart",
    "sessionId": "sessions/14341525286393884116",
    "title": "Refactor: RankingChart",
    "startTime": "2025-12-11T14:01:22.072221",
    "status": "created"
  }
]